pretix_log_read_access/__init__.py
pretix_log_read_access/middleware.py
pretix_log_read_access/signals.py
pretix_log_read_access/locale/de/LC_MESSAGES/django.mo
pretix_log_read_access/locale/de/LC_MESSAGES/django.po
pretix_log_read_access/locale/de_Informal/.gitkeep
pretix_log_read_access/locale/de_Informal/LC_MESSAGES/django.mo
pretix_log_read_access/locale/de_Informal/LC_MESSAGES/django.po
pretix_log_read_access/static/pretix_log_read_access/.gitkeep
pretix_log_read_access/templates/pretix_log_read_access/.gitkeep
pretix_log_read_access-1.1.0.dist-info/LICENSE
pretix_log_read_access-1.1.0.dist-info/METADATA
pretix_log_read_access-1.1.0.dist-info/WHEEL
pretix_log_read_access-1.1.0.dist-info/entry_points.txt
pretix_log_read_access-1.1.0.dist-info/top_level.txt
pretix_log_read_access-1.1.0.dist-info/RECORD
