Metadata-Version: 2.1
Name: pretix-log-read-access
Version: 1.1.0
Summary: This plugin logs any access to extended information (e.g. question answers) of a specific order, as well as all export jobs. No warranty for completeness given.
Home-page: https://github.com/pretix-unofficial/pretix-log-read-access
Author: pretix team
Author-email: support@pretix.eu
License: Apache
Platform: UNKNOWN
